{
  "pools": [
    {
      "entries": [
        {
          "functions": [
            {
              "count": 1,
              "function": "minecraft:set_count"
            }
          ],
          "name": "minecraft:diamond",
          "type": "minecraft:item",
          "weight": 2
        },
        {
          "functions": [
            {
              "count": 1,
              "function": "minecraft:set_count"
            }
          ],
          "name": "dungeons_gear:axe",
          "type": "minecraft:item",
          "weight": 2
        },
        {
          "functions": [
            {
              "count": 1,
              "function": "minecraft:set_count"
            }
          ],
          "name": "dungeons_gear:sword",
          "type": "minecraft:item",
          "weight": 3
        },
        {
          "functions": [
            {
              "count": 1,
              "function": "minecraft:set_count"
            }
          ],
          "name": "minecraft:shield",
          "type": "minecraft:item",
          "weight": 3
        },
        {
          "functions": [
            {
              "count": 1,
              "function": "minecraft:set_count"
            }
          ],
          "name": "minecraft:bow",
          "type": "minecraft:item",
          "weight": 3
        },
        {
          "functions": [
            {
              "count": 1,
              "function": "minecraft:set_count"
            }
          ],
          "name": "minecraft:crossbow",
          "type": "minecraft:item",
          "weight": 3
        },
        {
          "functions": [
            {
              "count": 1,
              "function": "minecraft:set_count"
            }
          ],
          "name": "minecraft:iron_helmet",
          "type": "minecraft:item",
          "weight": 3
        },
        {
          "functions": [
            {
              "count": 1,
              "function": "minecraft:set_count"
            }
          ],
          "name": "minecraft:iron_chestplate",
          "type": "minecraft:item",
          "weight": 3
        },
        {
          "functions": [
            {
              "count": 1,
              "function": "minecraft:set_count"
            }
          ],
          "name": "minecraft:iron_leggings",
          "type": "minecraft:item",
          "weight": 3
        },
        {
          "functions": [
            {
              "count": 1,
              "function": "minecraft:set_count"
            }
          ],
          "name": "minecraft:iron_boots",
          "type": "minecraft:item",
          "weight": 3
        }
      ],
      "rolls": {
        "max": 3.0,
        "min": 2.0,
        "type": "minecraft:uniform"
      }
    },
    {
      "entries": [
        {
          "functions": [
            {
              "count": {
                "max": 3.0,
                "min": 1.0,
                "type": "minecraft:uniform"
              },
              "function": "minecraft:set_count"
            }
          ],
          "name": "minecraft:iron_nugget",
          "type": "minecraft:item",
          "weight": 7
        },
        {
          "functions": [
            {
              "count": {
                "max": 3.0,
                "min": 1.0,
                "type": "minecraft:uniform"
              },
              "function": "minecraft:set_count"
            }
          ],
          "name": "minecraft:arrow",
          "type": "minecraft:item",
          "weight": 6
        },
        {
          "functions": [
            {
              "count": {
                "max": 2.0,
                "min": 1.0,
                "type": "minecraft:uniform"
              },
              "function": "minecraft:set_count"
            }
          ],
          "name": "minecraft:stick",
          "type": "minecraft:item",
          "weight": 9
        },
        {
          "functions": [
            {
              "count": {
                "max": 2.0,
                "min": 1.0,
                "type": "minecraft:uniform"
              },
              "function": "minecraft:set_count"
            }
          ],
          "name": "minecraft:string",
          "type": "minecraft:item",
          "weight": 8
        },
        {
          "functions": [
            {
              "count": {
                "max": 2.0,
                "min": 1.0,
                "type": "minecraft:uniform"
              },
              "function": "minecraft:set_count"
            }
          ],
          "name": "minecraft:cobblestone",
          "type": "minecraft:item",
          "weight": 7
        },
        {
          "functions": [
            {
              "count": 1,
              "function": "minecraft:set_count"
            }
          ],
          "name": "minecraft:rotten_flesh",
          "type": "minecraft:item",
          "weight": 6
        },
        {
          "functions": [
            {
              "count": 1,
              "function": "minecraft:set_count"
            }
          ],
          "name": "minecraft:experience_bottle",
          "type": "minecraft:item",
          "weight": 3
        },
        {
          "functions": [
            {
              "count": 1,
              "function": "minecraft:set_count"
            }
          ],
          "name": "minecraft:iron_ingot",
          "type": "minecraft:item",
          "weight": 3
        },
        {
          "functions": [
            {
              "count": 1,
              "function": "minecraft:set_count"
            }
          ],
          "name": "minecraft:chain",
          "type": "minecraft:item",
          "weight": 5
        }
      ],
      "rolls": {
        "max": 11.0,
        "min": 5.0,
        "type": "minecraft:uniform"
      }
    }
  ],
  "type": "minecraft:chest"
}