{
  "criteria": {
    "killed_fire_dragon": {
      "conditions": {
        "entity": {
          "type": "iceandfire:fire_dragon"
        }
      },
      "trigger": "minecraft:player_killed_entity"
    },
    "killed_ice_dragon": {
      "conditions": {
        "entity": {
          "type": "iceandfire:ice_dragon"
        }
      },
      "trigger": "minecraft:player_killed_entity"
    },
    "killed_lightning_dragon": {
      "conditions": {
        "entity": {
          "type": "iceandfire:lightning_dragon"
        }
      },
      "trigger": "minecraft:player_killed_entity"
    }
  },
  "display": {
    "description": {
      "translate": "advancements.iceandfire.kill_a_dragon.description"
    },
    "icon": {
      "item": "iceandfire:dragonbone"
    },
    "title": {
      "translate": "advancements.iceandfire.kill_a_dragon.title"
    }
  },
  "parent": "iceandfire:iceandfire/root",
  "requirements": [
    [
      "killed_fire_dragon",
      "killed_ice_dragon",
      "killed_lightning_dragon"
    ]
  ]
}