{
  "pools": [
    {
      "entries": [
        {
          "name": "dungeons_gear:the_last_laugh",
          "type": "minecraft:item"
        },
        {
          "name": "dungeons_gear:soul_fist",
          "type": "minecraft:item"
        },
        {
          "name": "dungeons_gear:suns_grace",
          "type": "minecraft:item"
        },
        {
          "name": "dungeons_gear:grave_bane",
          "type": "minecraft:item"
        },
        {
          "name": "dungeons_gear:soul_bow",
          "type": "minecraft:item"
        },
        {
          "name": "dungeons_gear:nocturnal_bow",
          "type": "minecraft:item"
        },
        {
          "name": "dungeons_gear:scatter_crossbow",
          "type": "minecraft:item"
        },
        {
          "name": "dungeons_gear:harp_crossbow",
          "type": "minecraft:item"
        },
        {
          "name": "dungeons_gear:thief_helmet",
          "type": "minecraft:item"
        },
        {
          "name": "dungeons_gear:thief_chestplate",
          "type": "minecraft:item"
        },
        {
          "name": "dungeons_gear:thief_leggings",
          "type": "minecraft:item"
        },
        {
          "name": "dungeons_gear:thief_boots",
          "type": "minecraft:item"
        },
        {
          "name": "dungeons_gear:spider_helmet",
          "type": "minecraft:item"
        },
        {
          "name": "dungeons_gear:spider_chestplate",
          "type": "minecraft:item"
        },
        {
          "name": "dungeons_gear:spider_leggings",
          "type": "minecraft:item"
        },
        {
          "name": "dungeons_gear:spider_boots",
          "type": "minecraft:item"
        },
        {
          "name": "dungeons_gear:gilded_glory_helmet",
          "type": "minecraft:item"
        },
        {
          "name": "dungeons_gear:gilded_glory_chestplate",
          "type": "minecraft:item"
        },
        {
          "name": "dungeons_gear:gilded_glory_leggings",
          "type": "minecraft:item"
        },
        {
          "name": "dungeons_gear:gilded_glory_boots",
          "type": "minecraft:item"
        }
      ],
      "rolls": 1
    }
  ],
  "type": "minecraft:chest"
}