{
  "criteria": {
    "Ender Dragon": {
      "conditions": {
        "entity": [
          {
            "condition": "minecraft:entity_properties",
            "entity": "this",
            "predicate": {
              "type": "minecraft:ender_dragon"
            }
          }
        ]
      },
      "trigger": "minecraft:player_killed_entity"
    },
    "Ender Guardian": {
      "conditions": {
        "entity": [
          {
            "condition": "minecraft:entity_properties",
            "entity": "this",
            "predicate": {
              "type": "cataclysm:ender_guardian"
            }
          }
        ]
      },
      "trigger": "minecraft:player_killed_entity"
    },
    "Obsidilith": {
      "conditions": {
        "entity": [
          {
            "condition": "minecraft:entity_properties",
            "entity": "this",
            "predicate": {
              "type": "bosses_of_mass_destruction:obsidilith"
            }
          }
        ]
      },
      "trigger": "minecraft:player_killed_entity"
    },
    "Void Worm": {
      "conditions": {
        "entity": [
          {
            "condition": "minecraft:entity_properties",
            "entity": "this",
            "predicate": {
              "type": "alexsmobs:void_worm"
            }
          }
        ]
      },
      "trigger": "minecraft:player_killed_entity"
    }
  },
  "display": {
    "description": {
      "translate": "advancements.panchoring.kill_all_bosses_end.description"
    },
    "frame": "challenge",
    "icon": {
      "item": "dungeons_gear:diamond_sword"
    },
    "title": {
      "translate": "advancements.panchoring.kill_all_bosses_end.title"
    }
  },
  "parent": "minecraft:end/kill_dragon",
  "rewards": {
    "experience": 500
  }
}