{
  "ingredients": [
    {
      "item": "minecraft:book"
    },
    {
      "item": "iceandfire:manuscript"
    },
    {
      "item": "iceandfire:manuscript"
    },
    {
      "item": "iceandfire:manuscript"
    },
    {
      "item": "iceandfire:manuscript"
    },
    {
      "item": "iceandfire:manuscript"
    },
    {
      "item": "iceandfire:manuscript"
    },
    {
      "item": "iceandfire:manuscript"
    },
    {
      "item": "ars_nouveau:mana_gem"
    }
  ],
  "result": {
    "item": "ars_nouveau:worn_notebook"
  },
  "type": "minecraft:crafting_shapeless"
}